dq_tools/__init__.py
dq_tools/builtins.py
dq_tools/core.py
dq_tools/reporting.py
dq_tools/yaml_runner.py
dq_tools-0.1.2.dist-info/licenses/LICENSE
dq_tools-0.1.2.dist-info/METADATA
dq_tools-0.1.2.dist-info/WHEEL
dq_tools-0.1.2.dist-info/top_level.txt
dq_tools-0.1.2.dist-info/RECORD
