Metadata-Version: 2.4
Name: dq-tools
Version: 0.1.2
Summary: Outil léger de data quality compatible avec DuckDB en mémoire
Author-email: Abdoul-Karim CAMARA <akcamara14@gmail.com>
License-Expression: MIT
Project-URL: Homepage, https://pypi.org/project/dq-tools/
Requires-Python: >=3.8
License-File: LICENSE
Requires-Dist: duckdb
Requires-Dist: pyyaml
Dynamic: license-file
